{
	"info": {
		"_postman_id": "portfolio-backend-api",
		"name": "Portfolio Backend API",
		"schema": "https://schema.getpostman.com/json/collection/v2.1.0/collection.json"
	},
	"item": [
		{
			"name": "Auth",
			"item": [
				{
					"name": "Register",
					"request": {
						"method": "POST",
						"header": [],
						"body": {
							"mode": "raw",
							"raw": "{\n    \"email\": \"admin@example.com\",\n    \"password\": \"admin123\"\n}",
							"options": {
								"raw": {
									"language": "json"
								}
							}
						},
						"url": {
							"raw": "{{base_url}}/auth/register",
							"host": [
								"{{base_url}}"
							],
							"path": [
								"auth",
								"register"
							]
						}
					},
					"response": []
				},
				{
					"name": "Login",
					"request": {
						"method": "POST",
						"header": [],
						"body": {
							"mode": "raw",
							"raw": "{\n    \"email\": \"admin@example.com\",\n    \"password\": \"admin123\"\n}",
							"options": {
								"raw": {
									"language": "json"
								}
							}
						},
						"url": {
							"raw": "{{base_url}}/auth/login",
							"host": [
								"{{base_url}}"
							],
							"path": [
								"auth",
								"login"
							]
						}
					},
					"response": []
				},
				{
					"name": "Logout",
					"request": {
						"method": "POST",
						"header": [],
						"url": {
							"raw": "{{base_url}}/auth/logout",
							"host": [
								"{{base_url}}"
							],
							"path": [
								"auth",
								"logout"
							]
						}
					},
					"response": []
				}
			]
		},
		{
			"name": "Projects",
			"item": [
				{
					"name": "Get All Projects",
					"request": {
						"method": "GET",
						"header": [],
						"url": {
							"raw": "{{base_url}}/projects",
							"host": [
								"{{base_url}}"
							],
							"path": [
								"projects"
							]
						}
					},
					"response": []
				},
				{
					"name": "Create Project",
					"request": {
						"method": "POST",
						"header": [],
						"body": {
							"mode": "raw",
							"raw": "{\n    \"title\": \"New Project\",\n    \"desc\": \"Description of the project\",\n    \"image\": \"https://via.placeholder.com/150\",\n    \"link\": \"https://github.com/example\",\n    \"tags\": [\"React\", \"Node\"]\n}",
							"options": {
								"raw": {
									"language": "json"
								}
							}
						},
						"url": {
							"raw": "{{base_url}}/projects",
							"host": [
								"{{base_url}}"
							],
							"path": [
								"projects"
							]
						}
					},
					"response": []
				},
				{
					"name": "Update Project",
					"request": {
						"method": "PUT",
						"header": [],
						"body": {
							"mode": "raw",
							"raw": "{\n    \"title\": \"Updated Project Title\"\n}",
							"options": {
								"raw": {
									"language": "json"
								}
							}
						},
						"url": {
							"raw": "{{base_url}}/projects/:id",
							"host": [
								"{{base_url}}"
							],
							"path": [
								"projects",
								":id"
							],
							"variable": [
								{
									"key": "id",
									"value": ""
								}
							]
						}
					},
					"response": []
				},
				{
					"name": "Delete Project",
					"request": {
						"method": "DELETE",
						"header": [],
						"url": {
							"raw": "{{base_url}}/projects/:id",
							"host": [
								"{{base_url}}"
							],
							"path": [
								"projects",
								":id"
							],
							"variable": [
								{
									"key": "id",
									"value": ""
								}
							]
						}
					},
					"response": []
				}
			]
		},
		{
			"name": "Skills",
			"item": [
				{
					"name": "Get All Skills",
					"request": {
						"method": "GET",
						"header": [],
						"url": {
							"raw": "{{base_url}}/skills",
							"host": [
								"{{base_url}}"
							],
							"path": [
								"skills"
							]
						}
					},
					"response": []
				},
				{
					"name": "Create Skill",
					"request": {
						"method": "POST",
						"header": [],
						"body": {
							"mode": "raw",
							"raw": "{\n    \"name\": \"Python\",\n    \"level\": \"Intermediate\",\n    \"icon\": \"python\"\n}",
							"options": {
								"raw": {
									"language": "json"
								}
							}
						},
						"url": {
							"raw": "{{base_url}}/skills",
							"host": [
								"{{base_url}}"
							],
							"path": [
								"skills"
							]
						}
					},
					"response": []
				}
			]
		},
		{
			"name": "Contacts",
			"item": [
				{
					"name": "Submit Contact",
					"request": {
						"method": "POST",
						"header": [],
						"body": {
							"mode": "raw",
							"raw": "{\n    \"name\": \"John Doe\",\n    \"email\": \"john@example.com\",\n    \"message\": \"Hello there!\"\n}",
							"options": {
								"raw": {
									"language": "json"
								}
							}
						},
						"url": {
							"raw": "{{base_url}}/contacts",
							"host": [
								"{{base_url}}"
							],
							"path": [
								"contacts"
							]
						}
					},
					"response": []
				},
				{
					"name": "List Contacts",
					"request": {
						"method": "GET",
						"header": [],
						"url": {
							"raw": "{{base_url}}/contacts",
							"host": [
								"{{base_url}}"
							],
							"path": [
								"contacts"
							]
						}
					},
					"response": []
				}
			]
		},
		{
			"name": "Social",
			"item": [
				{
					"name": "Get Socials",
					"request": {
						"method": "GET",
						"header": [],
						"url": {
							"raw": "{{base_url}}/social",
							"host": [
								"{{base_url}}"
							],
							"path": [
								"social"
							]
						}
					},
					"response": []
				},
				{
					"name": "Update Socials",
					"request": {
						"method": "PUT",
						"header": [],
						"body": {
							"mode": "raw",
							"raw": "{\n    \"github\": \"https://github.com/new\",\n    \"linkedin\": \"https://linkedin.com/new\"\n}",
							"options": {
								"raw": {
									"language": "json"
								}
							}
						},
						"url": {
							"raw": "{{base_url}}/social",
							"host": [
								"{{base_url}}"
							],
							"path": [
								"social"
							]
						}
					},
					"response": []
				}
			]
		},
		{
			"name": "Homepage",
			"item": [
				{
					"name": "Get Homepage",
					"request": {
						"method": "GET",
						"header": [],
						"url": {
							"raw": "{{base_url}}/homepage",
							"host": [
								"{{base_url}}"
							],
							"path": [
								"homepage"
							]
						}
					},
					"response": []
				},
				{
					"name": "Update Homepage",
					"request": {
						"method": "PUT",
						"header": [],
						"body": {
							"mode": "raw",
							"raw": "{\n    \"heroTitle\": \"New Title\",\n    \"heroSubtitle\": \"New Subtitle\",\n    \"aboutText\": \"New About Text\"\n}",
							"options": {
								"raw": {
									"language": "json"
								}
							}
						},
						"url": {
							"raw": "{{base_url}}/homepage",
							"host": [
								"{{base_url}}"
							],
							"path": [
								"homepage"
							]
						}
					},
					"response": []
				}
			]
		},
		{
			"name": "Analytics",
			"item": [
				{
					"name": "Get Stats",
					"request": {
						"method": "GET",
						"header": [],
						"url": {
							"raw": "{{base_url}}/analytics/stats",
							"host": [
								"{{base_url}}"
							],
							"path": [
								"analytics",
								"stats"
							]
						}
					},
					"response": []
				}
			]
		}
	],
	"variable": [
		{
			"key": "base_url",
			"value": "http://localhost:5000/api"
		}
	]
}
